jsmetrics/__init__.py
jsmetrics/details_for_all_metrics.py
jsmetrics/core/__init__.py
jsmetrics/core/check_data.py
jsmetrics/metrics/__init__.py
jsmetrics/metrics/jet_core_algorithms.py
jsmetrics/metrics/jet_core_algorithms_components.py
jsmetrics/metrics/jet_statistics.py
jsmetrics/metrics/jet_statistics_components.py
jsmetrics/metrics/waviness_metrics.py
jsmetrics/metrics/waviness_metrics_components.py
jsmetrics/utils/__init__.py
jsmetrics/utils/data_utils.py
jsmetrics/utils/spatial_utils.py
jsmetrics/utils/windspeed_utils.py
jsmetrics-0.3.1.dist-info/licenses/AUTHORS.rst
jsmetrics-0.3.1.dist-info/licenses/LICENSE
jsmetrics-0.3.1.dist-info/METADATA
jsmetrics-0.3.1.dist-info/WHEEL
jsmetrics-0.3.1.dist-info/top_level.txt
jsmetrics-0.3.1.dist-info/RECORD
