Metadata-Version: 2.4
Name: jsmetrics
Version: 0.3.1
Summary: Library of algorithms and metrics used to characterise jet streams.
Author-email: Thomas Keel <thomasjames.keel@gmail.com>
License: MIT License
Project-URL: Homepage, https://github.com/Thomasjkeel/jsmetrics
Keywords: jet-stream,climate,metrics,algorithms,xarray
Classifier: Development Status :: 4 - Beta
Classifier: Intended Audience :: Developers
Classifier: Intended Audience :: Science/Research
Classifier: License :: OSI Approved :: GNU General Public License v3 (GPLv3)
Classifier: Natural Language :: English
Classifier: Operating System :: OS Independent
Classifier: Programming Language :: Python :: 3
Classifier: Programming Language :: Python :: 3.10
Classifier: Programming Language :: Python :: 3.11
Classifier: Programming Language :: Python :: 3.12
Classifier: Programming Language :: Python :: 3.13
Classifier: Topic :: Scientific/Engineering :: Atmospheric Science
Requires-Python: >=3.10.0
License-File: LICENSE
License-File: AUTHORS.rst
Requires-Dist: numpy
Requires-Dist: pandas>=1.4
Requires-Dist: matplotlib>=3.3.2
Requires-Dist: xarray>=2023.1.0
Requires-Dist: scipy>=1.5.3
Requires-Dist: dask[array]
Requires-Dist: netCDF4>=1.5.5.1
Requires-Dist: bottleneck
Requires-Dist: numba
Requires-Dist: cf_xarray>=0.6.1
Requires-Dist: cftime>=1.4.1
Requires-Dist: Shapely
Provides-Extra: dev
Requires-Dist: bump2version; extra == "dev"
Requires-Dist: black; extra == "dev"
Requires-Dist: pytest; extra == "dev"
Requires-Dist: pytest-cov; extra == "dev"
Requires-Dist: flake8; extra == "dev"
Requires-Dist: parameterized; extra == "dev"
Requires-Dist: pre_commit; extra == "dev"
Requires-Dist: pylint; extra == "dev"
Requires-Dist: sphinx; extra == "dev"
Requires-Dist: numpydoc; extra == "dev"
Requires-Dist: sphinx-rtd-theme; extra == "dev"
Provides-Extra: data-install
Requires-Dist: cdsapi>=0.5.1; extra == "data-install"
Dynamic: license-file
